README.md
elb.py
setup.py
elb.py.egg-info/PKG-INFO
elb.py.egg-info/SOURCES.txt
elb.py.egg-info/dependency_links.txt
elb.py.egg-info/requires.txt
elb.py.egg-info/top_level.txt