Metadata-Version: 1.1
Name: elb.py
Version: 0.0.4
Summary: ELB python client
Home-page: https://github.com/projecteru2/elb
Author: ricebook
Author-email: timfeirg@ricebook.com
License: MIT
Platform: UNKNOWN
Classifier: License :: OSI Approved :: MIT License
Classifier: Programming Language :: Python
Classifier: Programming Language :: Python :: 3.6
Classifier: Programming Language :: Python :: Implementation :: CPython
